geeltermap/__init__.py
geeltermap/algorithms/__init__.py
geeltermap/basemaps.py
geeltermap/cartoee.py
geeltermap/chart.py
geeltermap/cli.py
geeltermap/colormaps.py
geeltermap/common.py
geeltermap/conversion.py
geeltermap/core.py
geeltermap/data/census_data.json
geeltermap/data/fonts/alibaba.otf
geeltermap/data/fonts/arial.ttf
geeltermap/data/gee_f.json
geeltermap/data/javascripts/ClippedComposite.js
geeltermap/data/javascripts/FromName.js
geeltermap/data/javascripts/ModisQaBands.js
geeltermap/data/javascripts/NormalizedDifference.js
geeltermap/data/javascripts/QualityMosaic.js
geeltermap/data/python/javascript_to_python.py
geeltermap/data/template/NLCD.qml
geeltermap/data/template/ee_api_docs.csv
geeltermap/data/template/ee_api_docs.html
geeltermap/data/template/ee_data_catalog.csv
geeltermap/data/template/ee_legend_table.txt
geeltermap/data/template/legend.html
geeltermap/data/template/legend.txt
geeltermap/data/template/legend_style.html
geeltermap/data/template/template.py
geeltermap/data/template/toolbox.csv
geeltermap/datasets.py
geeltermap/deck.py
geeltermap/ee_tile_layers.py
geeltermap/elter.py
geeltermap/examples/__init__.py
geeltermap/examples/datasets.txt
geeltermap/foliumap.py
geeltermap/geeltermap.py
geeltermap/geemap.py
geeltermap/heremap.py
geeltermap/kepler.py
geeltermap/legends.py
geeltermap/map_widgets.py
geeltermap/ml.py
geeltermap/osm.py
geeltermap/plot.py
geeltermap/plotlymap.py
geeltermap/report.py
geeltermap/timelapse.py
geeltermap/toolbar.py
geeltermap-0.1.9.dist-info/LICENSE
geeltermap-0.1.9.dist-info/METADATA
geeltermap-0.1.9.dist-info/WHEEL
geeltermap-0.1.9.dist-info/RECORD
