Metadata-Version: 2.1
Name: geeltermap
Version: 0.1.9
Summary: Python mapping application based on Geemap and GEE designed to provide phenology, flood and LST satellite data to eLTER sites
Home-page: https://github.com/Digdgeo/GeeLTERMap
License: MIT
Keywords: eLTER,Phenology,Flood,LST,GEE,Geemap,Python
Author: Diego García Díaz
Author-email: digd.geografo@gmail.com
Maintainer: Diego García Díaz
Maintainer-email: digd.geografo@gmail.com
Requires-Python: >=3.8,<4.0
Classifier: License :: OSI Approved :: MIT License
Classifier: Programming Language :: Python :: 3
Classifier: Programming Language :: Python :: 3.8
Classifier: Programming Language :: Python :: 3.9
Classifier: Programming Language :: Python :: 3.10
Classifier: Programming Language :: Python :: 3.11
Classifier: Programming Language :: Python :: 3.12
Classifier: Programming Language :: Python :: 3.13
Requires-Dist: deims (>=3.1,<4.0)
Requires-Dist: geedim (>=1.7.1,<2.0.0)
Requires-Dist: geemap (>=0.29.0,<0.30.0)
Requires-Dist: geopandas (>=0.12.2,<0.13.0)
Requires-Dist: ndvi2gif (>=0.0.5,<0.0.6)
Requires-Dist: pyproj (>=3.4.1,<4.0.0)
Requires-Dist: rasterio (>=1.3.6,<2.0.0)
Requires-Dist: requests (>=2.28.2,<3.0.0)
Project-URL: Repository, https://github.com/Digdgeo/GeeLTERMap
